babycam/__init__.py
babycam/camera_server.py
babycam/main.py
babycam/motion_detection.py
babycam/mqtt_handler.py
babycam/signal_handler.py
babycam/streaming.py
babycam/utils.py
rpi_babycam-1.0.0.dist-info/licenses/LICENSE
rpi_babycam-1.0.0.dist-info/WHEEL
rpi_babycam-1.0.0.dist-info/entry_points.txt
rpi_babycam-1.0.0.dist-info/METADATA
rpi_babycam-1.0.0.dist-info/RECORD
