Metadata-Version: 2.4
Name: rpi-babycam
Version: 1.0.0
Summary: A video streaming server and motion detector for Raspberry Pi.
Author: otter_rocket
License-Expression: AGPL-3.0
License-File: LICENSE
Classifier: Programming Language :: Python :: 3
Classifier: Operating System :: OS Independent
Requires-Dist: picamera2
Requires-Dist: numpy
Requires-Dist: opencv-python-headless
Requires-Dist: rich
Requires-Dist: click
Requires-Python: >=3.9
Project-URL: Bugs, https://codeberg.org/otter_rocket/rpi-babycam/issues
Project-URL: Homepage, https://codeberg.org/otter_rocket/rpi-babycam
